AUTHORS.rst
CONTRIBUTING.rst
HISTORY.rst
MANIFEST.in
README.rst
setup.cfg
setup.py
demopackage2/__init__.py
demopackage2/demopackage.py
demopackage2.egg-info/PKG-INFO
demopackage2.egg-info/SOURCES.txt
demopackage2.egg-info/dependency_links.txt
demopackage2.egg-info/not-zip-safe
demopackage2.egg-info/top_level.txt
docs/Makefile
docs/authors.rst
docs/conf.py
docs/contributing.rst
docs/history.rst
docs/index.rst
docs/installation.rst
docs/make.bat
docs/readme.rst
docs/usage.rst
tests/__init__.py
tests/test_demopackage.py