Metadata-Version: 1.2
Name: demopackage2
Version: 0.1.0
Summary: This is a demo package
Home-page: https://github.com/anu-coder/demopackage2
Author: Anurima Dey
Author-email: itzanurima@gmail.com
License: UNKNOWN
Keywords: demopackage2
Platform: UNKNOWN
Classifier: Development Status :: 2 - Pre-Alpha
Classifier: Intended Audience :: Developers
Classifier: Natural Language :: English
Classifier: Programming Language :: Python :: 3
Classifier: Programming Language :: Python :: 3.5
Classifier: Programming Language :: Python :: 3.6
Classifier: Programming Language :: Python :: 3.7
Classifier: Programming Language :: Python :: 3.8
Requires-Python: >=3.5
